[
    {
        "movie_name": "WALL-E",
        "rating": "G",
        "Genre": [
            "Animation,",
            "Sci-fi,",
            "Adventure,",
            "Comedy,",
            "Kids",
            "&",
            "family"
        ],
        "language": "English",
        "director": [
            " AndrewStanton"
        ],
        "producer": [
            "Jim",
            "Morris"
        ],
        "runtime": 97
    },
    {
        "cast name": "Ben Burtt"
    },
    {
        "cast name": "Elissa Knight"
    },
    {
        "cast name": "Jeff Garlin"
    },
    {
        "cast name": "Fred Willard"
    },
    {
        "cast name": "John Ratzenberger"
    },
    {
        "cast name": "Kathy Najimy"
    },
    {
        "cast name": "Sigourney Weaver"
    },
    {
        "cast name": "Bob Bergen"
    },
    {
        "cast name": "Andrew Stanton"
    },
    {
        "cast name": "Andrew Stanton"
    },
    {
        "cast name": "Jim Reardon"
    },
    {
        "cast name": "Jim Morris"
    },
    {
        "cast name": "Thomas Newman"
    },
    {
        "cast name": "Thomas Newman"
    },
    {
        "cast name": "Peter Gabriel"
    },
    {
        "cast name": "John Lasseter"
    },
    {
        "cast name": "Ralph Eggleston"
    },
    {
        "cast name": "Jeremy Lasky"
    },
    {
        "cast name": "Danielle Feinberg"
    },
    {
        "cast name": "Kevin Reher"
    },
    {
        "cast name": "Natalie Lyon"
    }
]
